{
    "collections": [
        {
            "ids": [
                "28560",
                "20684",
                "14655",
                "64818",
                "80607",
                "16571",
                "90048",
                "76571",
                "120154",
                "13742",
                "65290",
                "35620",
                "6762",
                "259172",
                "8991",
                "87045",
                "152437",
                "8987",
                "869",
                "4796",
                "81512",
                "193664",
                "43145",
                "111610",
                "14598",
                "25865",
                "154235",
                "69780",
                "81558",
                "109780"
            ],
            "key": "artic_impressionism",
            "name": "Impressionism & Post-Impressionism",
            "name_translations": {
                "en": "Impressionism & Post-Impressionism",
                "fr": "Impressionnisme et postimpressionnisme",
                "zh": "印象派与后印象派"
            },
            "type": "curated"
        },
        {
            "ids": [
                "90048",
                "76571",
                "120154",
                "13742",
                "65290"
            ],
            "name": "American Art",
            "name_translations": {
                "da": "Amerikansk Kunst",
                "de": "Amerikanische Kunst",
                "es": "Arte Americano",
                "fr": "Art Américain",
                "it": "Arte Americana",
                "ja": "アメリカ美術",
                "ko": "미국 미술",
                "nl": "Amerikaanse Kunst",
                "ru": "Американское Искусство",
                "zh-CN": "美国艺术",
                "zh-TW": "美國藝術"
            },
            "key": "artic_american",
            "type": "curated"
        },
        {
            "ids": [
                "35620",
                "6762",
                "259172"
            ],
            "name": "Asian Art",
            "name_translations": {
                "da": "Asiatisk Kunst",
                "de": "Asiatische Kunst",
                "es": "Arte Asiático",
                "fr": "Art Asiatique",
                "it": "Arte Asiatica",
                "ja": "アジア美術",
                "ko": "아시아 미술",
                "nl": "Aziatische Kunst",
                "ru": "Азиатское Искусство",
                "zh-CN": "亚洲艺术",
                "zh-TW": "亞洲藝術"
            },
            "key": "artic_asian",
            "type": "curated"
        },
        {
            "ids": [
                "869",
                "4796",
                "81512",
                "193664",
                "43145",
                "111610",
                "28862",
                "57996",
                "39560",
                "107938",
                "160229",
                "111074",
                "16370",
                "146272",
                "68769",
                "147508",
                "108575",
                "71154",
                "120061",
                "58653",
                "105798",
                "189317",
                "135746",
                "277825",
                "106377",
                "112092",
                "106279",
                "112066",
                "112080",
                "112113",
                "106307"
            ],
            "name": "European Painting & Sculpture",
            "name_translations": {
                "da": "Europæisk Maleri og Skulptur",
                "de": "Europäische Malerei und Skulptur",
                "es": "Pintura y Escultura Europea",
                "fr": "Peinture et Sculpture Européennes",
                "it": "Pittura e Scultura Europea",
                "ja": "ヨーロッパ絵画と彫刻",
                "ko": "유럽 회화 및 조각",
                "nl": "Europese Schilder- en Beeldhouwkunst",
                "ru": "Европейская Живопись и Скульптура",
                "zh-CN": "欧洲绘画与雕塑",
                "zh-TW": "歐洲繪畫與雕塑"
            },
            "key": "artic_european",
            "type": "curated"
        },
        {
            "ids": [
                "28560",
                "20684",
                "14655",
                "64818",
                "80607",
                "16571",
                "90048",
                "76571",
                "120154",
                "13742",
                "65290",
                "35620",
                "6762",
                "259172",
                "8991",
                "87045",
                "152437",
                "8987",
                "869",
                "4796",
                "81512",
                "193664",
                "43145",
                "111610",
                "14598",
                "25865",
                "154235",
                "69780",
                "81558",
                "109780"
            ],
            "name": "⭐ Best of AIC",
            "name_translations": {
                "da": "⭐ Det Bedste fra AIC",
                "de": "⭐ Das Beste aus dem AIC",
                "es": "⭐ Lo Mejor del AIC",
                "fr": "⭐ Le Meilleur de l'AIC",
                "it": "⭐ Il Meglio dell'AIC",
                "ja": "⭐ AICの名作",
                "ko": "⭐ AIC 베스트",
                "nl": "⭐ Het Beste van AIC",
                "ru": "⭐ Лучшее из AIC",
                "zh-CN": "⭐ 芝加哥艺术博物馆精选",
                "zh-TW": "⭐ 芝加哥藝術博物館精選"
            },
            "key": "artic_highlights",
            "type": "curated"
        },
        {
            "ids": [
                "8991",
                "87045",
                "152437",
                "8987"
            ],
            "name": "Modern & Contemporary Art",
            "name_translations": {
                "da": "Moderne og Samtidskunst",
                "de": "Moderne & Zeitgenössische Kunst",
                "es": "Arte Moderno y Contemporáneo",
                "fr": "Art Moderne et Contemporain",
                "it": "Arte Moderna e Contemporanea",
                "ja": "近現代美術",
                "ko": "근현대 미술",
                "nl": "Moderne en Hedendaagse Kunst",
                "ru": "Современное Искусство",
                "zh-CN": "现代与当代艺术",
                "zh-TW": "現代與當代藝術"
            },
            "key": "artic_modern",
            "type": "curated"
        }
    ],
    "description": "Art Institute of Chicago: Curated Masterpieces",
    "version": "v2.6.0"
}